{"name": "John Smith", "birth_date": "11.11.2001", "birth_place": "Berlin", "address": "Amsterdam", "phone": "123456789", "passport": "22 55 77567868", "pass_date": "10.10.2011", "license": "55 6779089", "license_date": "21.12.2020", "name2": "John Silver", "birth_date2": "21.10.2002", "birth_place2": "London", "address2": "Amsterdam", "phone2": "6788789789", "passport2": "44 11 343453456", "pass_date2": "11.11.2011", "license2": "77 77834234", "license_date2": "21.10.2014", "car_type": "Nissan", "car_number": "A490BU", "rent_begin": "15.03.2022 19:14", "rent_end": "10.08.2022", "rent_days": "30", "price_km": "5", "start_place": "Amsterdam", "return_place": "Amsterdam", "company_name": "Company name", "pdv": "897689323", "price": "30", "tax": "7", "payment_type": "CASH", "discount": "55", "full_price": "900", "deposit": "77", "fuel_type": "BMB95", "can_abroad": 0, "documents": 1, "firstaid": 1, "insurance": 1, "triangle": 1, "wifi_router": 1, "navigator": 0, "domkrate": 1, "lamps": 1, "spare_tire": 0, "cchair": 1, "buster": 1, "defects": 1}